Workbook

Sheet Исходные данные
A1: Фонд рабочего времени | B1: 168.8 | D1: Годовой фонд заработной платы диспетчера
A2: Тарифный коэффициент | B2: 2.84 | D2: Основная заработная плата разработчиков продукта | E2: 600
A3: Месячный оклад | B3: 500 | D3: Дополнительная заработная плата разработчиков продукта | E3: =E2*B5 -> 120
A4: Количество рабочих часов | B4: 6 | D4: Отчисления в фонд социальной защиты населения | E4: =(E2+E3)*B6 -> 244.8
A5: Дополнительная заработная плата | B5: 0.2 | D5: Отчисления в Белгосстрах | E5: =(E2+E3)*B7 -> 4.32
A6: ФСЗН | B6: 0.34 | D6: ИТОГО | E6: =SUM(E2:E5) -> 969.12
A7: Белгосстрах | B7: 0.006 | D7: ИТОГО за год | E7: =E6*12 -> 11629.44
A8: Косвенные расходы | B8: 0.65
A9: Экономия времени | B9: ='Экономия времени'!I7 -> 752
A10: К | B10: ='Экономия времени'!I7/'Исходные данные'!B11 -> 4.6040816
A11: Годовой фонд времени | B11: =980/6 -> 163.33333
A12: Отпускная цена программного продукта | B12: =Калькуляция!D14 -> 2540.4944
A13: Условная экономия | B13: =E7*B10 -> 53542.891
A14: Экономический эффект | B14: =B13-B12 -> 51002.397
A15: Рентабельность | B15: =B12/B14*100 -> 4.9811275

Sheet План работы
A1: План проведения научно-исследовательской работы
A2: № п/п | B2: Наименование этапов и видов работ | C2: Исполнитель (должность, квалификация) | D2: Количест-во исполнителей | E2: Трудоемкость, чело веко-дни,tож
A3: 1 | B3: 2 | C3: 3 | D3: 4 | E3: 5
A4: 1 | B4: Разработка постановки задачи, организационно-экономическая сущность программы, определение входной, постоянной, выходной информации, выбор математической модели. Выбор операционной системы, выбор языка программирования и системы управления базы данных. | C4: Техник-программист | D4: 1 | E4: 2
A5: 2 | B5: Разработка и отладка программного продукта. Испытание программы. | C5: Техник-программист | D5: 1 | E5: 13
A6: 3 | B6: Оформление проектной документации. | C6: Техник-программист | D6: 1 | E6: 2
A7: 4 | B7: Работа над разделом энергосбережения и охрана труда. | C7: Техник-программист | D7: 1 | E7: 3
A8: 5 | B8: Работа над экономическим разделом. | C8: Техник-программист | D8: 1 | E8: 2
A9: 6 | B9: Оформление пояснительной записки. | C9: Техник-программист | D9: 1 | E9: 2
B10: Итого: | E10: =SUM(E4:E9) -> 24

Sheet Трудоемкость
A1: Таблица 26 - Оценка трудоемкости
A2: Вид работы | B2: Оценка трудоемкости | E2: Расчетные величины
B3: tmin | C3: tH.B | D3: tmax | E3: tож | F3: D
A4: 1 | B4: =C4-1 -> 1 | C4: ='План работы'!E4 -> 2 | D4: 2 | E4: =(B4+4*C4+D4)/6 -> 1.8333333 | F4: =((D4-B4)/6)^2 -> 0.027777778
A5: 2 | B5: =C5-1 -> 12 | C5: ='План работы'!E5 -> 13 | D5: =C5+1 -> 14 | E5: =(B5+4*C5+D5)/6 -> 13 | F5: =((D5-B5)/6)^2 -> 0.11111111
A6: 3 | B6: 1 | C6: ='План работы'!E6 -> 2 | D6: =C6+1 -> 3 | E6: =(B6+4*C6+D6)/6 -> 2 | F6: =((D6-B6)/6)^2 -> 0.11111111
A7: 4 | B7: 1 | C7: ='План работы'!E7 -> 3 | D7: 4 | E7: =(B7+4*C7+D7)/6 -> 2.8333333 | F7: =((D7-B7)/6)^2 -> 0.25
A8: 5 | B8: =C8-1 -> 1 | C8: ='План работы'!E8 -> 2 | D8: 2 | E8: =(B8+4*C8+D8)/6 -> 1.8333333 | F8: =((D8-B8)/6)^2 -> 0.027777778
A9: 6 | B9: 1 | C9: ='План работы'!E9 -> 2 | D9: 2 | E9: =(B9+4*C9+D9)/6 -> 1.8333333 | F9: =((D9-B9)/6)^2 -> 0.027777778
A10: Итого: | B10: =SUM(B4:B9) -> 17 | C10: =SUM(C4:C9) -> 24 | D10: =SUM(D4:D9) -> 27 | E10: =SUM(E4:E9) -> 23.333333 | F10: =((D10-B10)/6)^2 -> 2.7777778

Sheet Ленточный график
A1: 27 - Ленточный график создания программного продукта
A2: № п/п | B2: Наименование этапов и видов работ | C2: Исполнитель (должность, квалификация) | D2: Трудоемкость, чело веко-дни,tож
A3: 1 | B3: 2 | C3: 3 | D3: 4
A4: 1 | B4: Разработка постановки задачи, организационно-экономическая сущность программы, определение входной, постоянной, выходной информации, выбор математической модели. Выбор операционной системы, выбор языка программирования и системы управления базы данных. | C4: Техник-программист | D4: 3
A5: 2 | B5: Разработка и отладка программного продукта. Испытание программы. | C5: Техник-программист | D5: 12
A6: 3 | B6: Оформление проектной документации. | C6: Техник-программист | D6: ='План работы'!E6 -> 2
A7: 4 | B7: Работа над разделом энергосбережения и охрана труда. | C7: Техник-программист | D7: 2
A8: 5 | B8: Работа над экономическим разделом. | C8: Техник-программист | D8: ='План работы'!E8 -> 2
A9: 6 | B9: Оформление пояснительной записки. | C9: Техник-программист | D9: 3

Sheet Основная зп
A1: Определение суммы основной заработной платы
A2: Вид работ | B2: Трудоемкость, чел/дни | C2: Дневная ставка, бел.руб | D2: Сумма основной заработной платы, бел. руб.
A3: 1 | B3: 2 | C3: 3 | D3: 4
A4: Разработка постановки задачи, организационно-экономическая сущность программы, определение входной информации, выбор математической модели. Выбор операционной системы, выбор языка программирования и системы управления баз данных. | B4: ='План работы'!E4 -> 2 | C4: ='Исходные данные'!B3*'Исходные данные'!B2/'Исходные данные'!B1*'Исходные данные'!B4 -> 50.473934 | D4: =C4*B4 -> 100.94787
A5: Разработка и отладка программного продукта. Испытание программы. | B5: ='План работы'!E5 -> 13 | C5: ='Исходные данные'!B3*'Исходные данные'!B2/'Исходные данные'!B1*'Исходные данные'!B4 -> 50.473934 | D5: =C5*B5 -> 656.16114
A6: Оформление проектной документации. | B6: ='План работы'!E6 -> 2 | C6: ='Исходные данные'!B3*'Исходные данные'!B2/'Исходные данные'!B1*'Исходные данные'!B4 -> 50.473934 | D6: =C6*B6 -> 100.94787
A7: Работа над разделом экология и охрана труда. | B7: ='План работы'!E7 -> 3 | C7: ='Исходные данные'!B3*'Исходные данные'!B2/'Исходные данные'!B1*'Исходные данные'!B4 -> 50.473934 | D7: =C7*B7 -> 151.4218
A8: Работа над экономическим разделом. | B8: ='План работы'!E8 -> 2 | C8: ='Исходные данные'!B3*'Исходные данные'!B2/'Исходные данные'!B1*'Исходные данные'!B4 -> 50.473934 | D8: =C8*B8 -> 100.94787
A9: Оформление пояснительной записки | B9: ='План работы'!E9 -> 2 | C9: ='Исходные данные'!B3*'Исходные данные'!B2/'Исходные данные'!B1*'Исходные данные'!B4 -> 50.473934 | D9: =C9*B9 -> 100.94787
A10: Итого: | B10: ='План работы'!E10 -> 24 | C10: =SUM(C4:C9) -> 302.8436 | D10: =SUM(D4:D9) -> 1211.3744

Sheet Калькуляция
A1: Форма калькуляции плановой себестоимости
A2: № | B2: Статьи затрат | C2: Условное обозначение | D2: Сумма затрат, руб.
A3: 1 | B3: 2 | C3: 3 | D3: 4
A4: 1 | B4: Материалы и оборудование | D4: 0
A5: 2 | B5: Расходы на оплату труда:
A6: 2.1 | B6: Основная заработная плата разработчиков продукта | D6: ='Основная зп'!D10 -> 1211.3744
A7: 2.2 | B7: Дополнительная заработная плата разработчиков продукта | D7: =D6*'Исходные данные'!B5 -> 242.27488
A8: 3 | B8: Отчисления на социальные нужды:
A9: 3.1 | B9: Отчисления в фонд социальной защиты населения | D9: =(D6+D7)*'Исходные данные'!B5 -> 290.72986
A10: 3.2 | B10: Отчисления в Белгосстрах | C10: Об | D10: =(D6+D7)*'Исходные данные'!B7 -> 8.7218957
A11: 4 | B11: Косвенные накладные расходы | D11: =D6*'Исходные данные'!B8 -> 787.39336
A12: 5 | B12: Полная себестоимость | D12: =SUM(D4:D11) -> 2540.4944
A13: 6 | B13: Налог на добавленную стоимость | C13: НДС
A14: 7 | B14: Отпускная цена программного продукта | D14: =D12 -> 2540.4944

Sheet Экономия времени
A1: Определение экономии времени | F1: Определение годового фонда времени
A2: Перечень услуг программного продукта | B2: Время до автоматизации, ч | C2: Время после автоматизации, ч | D2: Экономия времени, ч | F2: Перечень услуг программного продукта | G2: Количество операций в полгода | H2: Экономия времени, ч | I2: Полугодовой фонд времени, ч
A3: 1 Ввод даных в базу данных | B3: 1 | C3: 0.5 | D3: =B3-C3 -> 0.5 | F3: 1 Ввод даных в базу данных | G3: 500 | H3: =D3 -> 0.5 | I3: =H3*G3 -> 250
A4: 2. Учет количества нарушителей | B4: 1 | C4: 0.5 | D4: =B4-C4 -> 0.5 | F4: 2. Учет количества нарушителей | G4: 500 | H4: =D4 -> 0.5 | I4: =H4*G4 -> 250
A5: 3. Учет нарушений | B5: 0.3 | C5: 0.1 | D5: =B5-C5 -> 0.2 | F5: 3. Учет нарушений | G5: 10 | H5: =D5 -> 0.2 | I5: =H5*G5 -> 2
A6: 4. Формирование отчетов | B6: 1 | C6: 0.5 | D6: =B6-C6 -> 0.5 | F6: 4. Формирование отчетов | G6: 500 | H6: =D6 -> 0.5 | I6: =H6*G6 -> 250
A7: Итого: | B7: =SUM(B3:B6) -> 3.3 | C7: =SUM(C3:C6) -> 1.6 | D7: =B7-C7 -> 1.7 | F7: Итого: | G7: =SUM(G3:G6) -> 1510 | H7: =SUM(H3:H6) -> 1.7 | I7: =SUM(I3:I6) -> 752
